fpcap/__init__.py
fpcap/capture_pcap.py
pyFpcap-1.2.0.dist-info/DESCRIPTION.rst
pyFpcap-1.2.0.dist-info/METADATA
pyFpcap-1.2.0.dist-info/RECORD
pyFpcap-1.2.0.dist-info/WHEEL
pyFpcap-1.2.0.dist-info/metadata.json
pyFpcap-1.2.0.dist-info/top_level.txt
tests/__init__.py
tests/test.py
