Metadata-Version: 2.0
Name: pyFpcap
Version: 1.2.0
Summary: A pure Python library designed to make it easy and quick to capture RTP on FREESWITCH's established session
Home-page: https://github.com/sudaning/Fpcap
Author: Daning Su
Author-email: sudaning@sina.com
License: LICENSE
Platform: linux
Classifier: Development Status :: 5 - Production/Stable
Classifier: Intended Audience :: Science/Research
Classifier: Natural Language :: Chinese (Simplified)
Classifier: Topic :: Text Processing
Classifier: Operating System :: POSIX :: Linux
Classifier: License :: OSI Approved :: MIT License
Classifier: Programming Language :: Python :: 2
Classifier: Programming Language :: Python :: 2.7
Requires-Dist: pyFneko (>=3.4)
